skeletorch/__init__.py
skeletorch/skeletorch.py
skeletorch-0.1.1.dist-info/LICENSE
skeletorch-0.1.1.dist-info/METADATA
skeletorch-0.1.1.dist-info/WHEEL
skeletorch-0.1.1.dist-info/top_level.txt
skeletorch-0.1.1.dist-info/RECORD
