Metadata-Version: 2.1
Name: skeletorch
Version: 0.1.1
Summary: Pytorch implementation of skeleton transformer module
Home-page: https://github.com/Yutsuro/skeleton-transformer-Pytorch
Author: Yutsuro
Author-email: Yuki@utsu.ro
License: MIT
Keywords: Skeleton-Transformer Python Pytorch Action-Recognition Skeleton Pose-Estimation
Classifier: License :: OSI Approved :: MIT License
Classifier: Programming Language :: Python :: 3
Classifier: Programming Language :: Python :: 3.6
Classifier: Programming Language :: Python :: 3.7
Classifier: Programming Language :: Python :: 3.8
Classifier: Programming Language :: Python :: 3.9
Classifier: Programming Language :: Python :: 3 :: Only
Classifier: Topic :: Software Development :: Libraries :: Python Modules
License-File: LICENSE
Requires-Dist: filelock (==3.9.0)
Requires-Dist: mpmath (==1.2.1)
Requires-Dist: networkx (==3.0)
Requires-Dist: numpy (==1.24.1)
Requires-Dist: Pillow (==9.3.0)
Requires-Dist: sympy (==1.11.1)
Requires-Dist: torch (==2.0.0+cu117)
Requires-Dist: torchaudio (==2.0.1+cu117)
Requires-Dist: torchvision (==0.15.1+cu117)
Requires-Dist: typing-extensions (==4.4.0)
Requires-Dist: urllib3 (==1.26.13)
